README.md
setup.cfg
setup.py
chtools/__init__.py
chtools.egg-info/PKG-INFO
chtools.egg-info/SOURCES.txt
chtools.egg-info/dependency_links.txt
chtools.egg-info/entry_points.txt
chtools.egg-info/requires.txt
chtools.egg-info/top_level.txt
chtools/aws_account/__init__.py
chtools/aws_account/cli.py
chtools/aws_account/client.py
chtools/aws_account/data.py
chtools/cli/__init__.py
chtools/cli/cli.py
chtools/cli/file.py
chtools/cli/handler.py
chtools/cloudhealth/__init__.py
chtools/cloudhealth/client.py
chtools/perspective/__init__.py
chtools/perspective/cli.py
chtools/perspective/client.py
chtools/perspective/data.py
tests/__init__.py
tests/test_aws_account_cli.py
tests/test_aws_account_client.py
tests/test_perspective_cli.py
tests/test_perspective_client.py
tests/test_perspective_data.py