Metadata-Version: 2.1
Name: chtools
Version: 2.3.1
Summary: Automation Tools for CloudHealth
Home-page: https://github.com/bluechiptek/cloudhealth-tools
Author: BlueChipTek
Author-email: joe@bluechiptek.com
License: GPLv3
Platform: UNKNOWN
Classifier: License :: OSI Approved :: GNU General Public License v3 (GPLv3)
Classifier: Programming Language :: Python :: 3 :: Only
Requires-Python: >=3
